easyexception/__init__.py
easyexception/exception.py
easyexception-0.0.3.dist-info/LICENSE
easyexception-0.0.3.dist-info/METADATA
easyexception-0.0.3.dist-info/WHEEL
easyexception-0.0.3.dist-info/top_level.txt
easyexception-0.0.3.dist-info/RECORD
