Metadata-Version: 2.1
Name: easyexception
Version: 0.0.3
Summary: Easy-to-use custom error/warning/message exceptions.
Home-page: https://pypi.python.org/pypi/easyexception
Author: Ao Liu, Jie Gao
Author-email: ao@aoliu.tech, geographer2008@gmail.com
License: MIT
Keywords: Exception,Easy
Platform: UNKNOWN
Classifier: Development Status :: 1 - Planning
Classifier: Operating System :: OS Independent
Classifier: Topic :: Utilities
Classifier: License :: OSI Approved :: MIT License
Classifier: Programming Language :: Python :: 3
Requires-Python: >=3.0
